{"tonicHz":155.66,"start":273.614,"end":293.791,"file":"audio/eikev-1.mp3","words":[{"i":0,"start":273.614,"end":275.17,"steps":[{"t0":0.281,"t1":0.474,"p":4.83},{"t0":0.564,"t1":0.641,"p":4.81},{"t0":0.706,"t1":0.976,"p":-1.71}]},{"i":1,"start":275.17,"end":276.749,"steps":[{"t0":0.115,"t1":0.318,"p":-2.08},{"t0":0.413,"t1":0.521,"p":-1.93},{"t0":0.571,"t1":0.666,"p":4.62},{"t0":0.685,"t1":0.945,"p":1.55}]},{"i":2,"start":276.749,"end":278.374,"steps":[{"t0":0.217,"t1":0.42,"p":1.51},{"t0":0.426,"t1":0.531,"p":4.37},{"t0":0.611,"t1":0.919,"p":-0.29}]},{"i":3,"start":278.374,"end":280.554,"steps":[{"t0":0.21,"t1":0.265,"p":1.67},{"t0":0.306,"t1":0.421,"p":1.53},{"t0":0.449,"t1":0.522,"p":1.22},{"t0":0.614,"t1":0.742,"p":1.66},{"t0":0.747,"t1":0.871,"p":0.1},{"t0":0.898,"t1":0.999,"p":4.91}]},{"i":4,"start":280.554,"end":280.797,"steps":[{"t0":0.65,"t1":0.979,"p":3.28}]},{"i":5,"start":280.797,"end":282.159,"steps":[{"t0":0.261,"t1":0.393,"p":0.94},{"t0":0.4,"t1":0.76,"p":0.11}]},{"i":6,"start":282.159,"end":283.552,"steps":[{"t0":0.282,"t1":0.426,"p":-0.17},{"t0":0.505,"t1":0.634,"p":1.93},{"t0":0.698,"t1":0.899,"p":-0.1}]},{"i":7,"start":283.552,"end":284.946,"steps":[{"t0":0.316,"t1":0.416,"p":-2.37},{"t0":0.438,"t1":0.818,"p":-0.18}]},{"i":8,"start":284.946,"end":285.385,"steps":[{"t0":0.788,"t1":0.811,"p":-1.59},{"t0":0.834,"t1":0.993,"p":-0.12}]},{"i":9,"start":285.385,"end":286.409,"steps":[{"t0":0.007,"t1":0.241,"p":-0.46},{"t0":0.397,"t1":0.466,"p":-0.36},{"t0":0.632,"t1":0.837,"p":-0.61}]},{"i":10,"start":286.409,"end":287.476,"steps":[{"t0":0.284,"t1":0.509,"p":4.76},{"t0":0.556,"t1":0.818,"p":1.94}]},{"i":11,"start":287.476,"end":289.078,"steps":[{"t0":0.147,"t1":0.203,"p":1.39},{"t0":0.291,"t1":0.397,"p":1.83},{"t0":0.434,"t1":0.559,"p":4.01},{"t0":0.647,"t1":0.921,"p":-0.25}]},{"i":12,"start":289.078,"end":290.123,"steps":[{"t0":0.434,"t1":0.741,"p":-0.44},{"t0":0.817,"t1":0.894,"p":-0.39}]},{"i":13,"start":290.123,"end":291.632,"steps":[{"t0":0.132,"t1":0.225,"p":-0.45},{"t0":0.311,"t1":0.417,"p":-0.34},{"t0":0.45,"t1":0.516,"p":-0.23},{"t0":0.589,"t1":0.682,"p":2.09},{"t0":0.715,"t1":0.914,"p":-0.48}]},{"i":14,"start":291.632,"end":293.791,"steps":[{"t0":0.139,"t1":0.259,"p":-0.39},{"t0":0.315,"t1":0.556,"p":1.68},{"t0":0.584,"t1":0.871,"p":-2.35}]}]}