{"tonicHz":163.19,"start":117.686,"end":142.255,"file":"audio/eikev-4.mp3","words":[{"i":0,"start":117.686,"end":119.149,"steps":[{"t0":0.353,"t1":0.489,"p":-1.55},{"t0":0.496,"t1":0.558,"p":-2.79},{"t0":0.633,"t1":0.968,"p":2.04}]},{"i":1,"start":119.149,"end":121.61,"steps":[{"t0":0.042,"t1":0.103,"p":1.77},{"t0":0.176,"t1":0.237,"p":2.78},{"t0":0.261,"t1":0.485,"p":0.03},{"t0":0.489,"t1":0.619,"p":-1.67},{"t0":0.623,"t1":0.745,"p":-2.7},{"t0":0.749,"t1":0.96,"p":-4.68}]},{"i":2,"start":121.61,"end":124.234,"steps":[{"t0":0.161,"t1":0.237,"p":0.3},{"t0":0.29,"t1":0.367,"p":0.64},{"t0":0.378,"t1":0.591,"p":-1.97},{"t0":0.595,"t1":0.729,"p":-3.07},{"t0":0.732,"t1":0.797,"p":-1.67},{"t0":0.801,"t1":0.934,"p":0.12}]},{"i":3,"start":124.234,"end":125.65,"steps":[{"t0":0.323,"t1":0.422,"p":-2.69},{"t0":0.472,"t1":0.705,"p":-2.54},{"t0":0.733,"t1":0.924,"p":0.34}]},{"i":4,"start":125.65,"end":126.487,"steps":[{"t0":0.349,"t1":0.922,"p":-0.25}]},{"i":5,"start":126.487,"end":127.531,"steps":[{"t0":0.091,"t1":0.187,"p":0.42},{"t0":0.292,"t1":0.512,"p":2.54},{"t0":0.551,"t1":0.934,"p":-0.02}]},{"i":6,"start":127.531,"end":129.415,"steps":[{"t0":0.181,"t1":0.271,"p":-2.12},{"t0":0.351,"t1":0.446,"p":-1.58},{"t0":0.452,"t1":0.717,"p":0.39}]},{"i":7,"start":129.415,"end":130.437,"steps":[{"t0":0.33,"t1":0.858,"p":0.58}]},{"i":8,"start":130.437,"end":131.319,"steps":[{"t0":0.357,"t1":0.584,"p":5.06},{"t0":0.686,"t1":0.788,"p":-3.07},{"t0":0.799,"t1":0.992,"p":-1.83}]},{"i":9,"start":131.319,"end":132.851,"steps":[{"t0":0.191,"t1":0.276,"p":-1.3},{"t0":0.283,"t1":0.485,"p":-2.02},{"t0":0.544,"t1":0.661,"p":4.55},{"t0":0.687,"t1":0.975,"p":2.08}]},{"i":10,"start":132.851,"end":134.941,"steps":[{"t0":0.187,"t1":0.221,"p":0.89},{"t0":0.225,"t1":0.311,"p":2.49},{"t0":0.417,"t1":0.675,"p":2.29},{"t0":0.699,"t1":0.847,"p":0.45},{"t0":0.876,"t1":0.996,"p":4.75}]},{"i":11,"start":134.941,"end":135.893,"steps":[{"t0":0.211,"t1":0.442,"p":2.03},{"t0":0.453,"t1":0.946,"p":0.43}]},{"i":12,"start":135.893,"end":138.517,"steps":[{"t0":0.16,"t1":0.209,"p":-2.75},{"t0":0.236,"t1":0.289,"p":-0.05},{"t0":0.327,"t1":0.404,"p":0.46},{"t0":0.419,"t1":0.667,"p":-1.81},{"t0":0.67,"t1":0.785,"p":-2.76},{"t0":0.788,"t1":0.846,"p":-1.65},{"t0":0.861,"t1":0.99,"p":0.29}]},{"i":13,"start":138.517,"end":139.817,"steps":[{"t0":0.312,"t1":0.427,"p":-2.99},{"t0":0.435,"t1":0.535,"p":-2.17},{"t0":0.542,"t1":0.65,"p":-2.93},{"t0":0.712,"t1":0.996,"p":0.19}]},{"i":14,"start":139.817,"end":140.746,"steps":[{"t0":0.135,"t1":0.328,"p":0.0},{"t0":0.382,"t1":0.522,"p":2.09},{"t0":0.565,"t1":0.92,"p":0.15}]},{"i":15,"start":140.746,"end":142.255,"steps":[{"t0":0.083,"t1":0.156,"p":0.86},{"t0":0.349,"t1":0.408,"p":2.62},{"t0":0.415,"t1":0.508,"p":1.81},{"t0":0.547,"t1":0.998,"p":-1.57}]}]}